clgui/Layouts.py
clgui/__init__.py
clgui/clgui.py
clgui/layout.py
clgui-0.1.2.dist-info/licenses/LICENSE
clgui-0.1.2.dist-info/licenses/LICENSE.txt
clgui-0.1.2.dist-info/METADATA
clgui-0.1.2.dist-info/WHEEL
clgui-0.1.2.dist-info/top_level.txt
clgui-0.1.2.dist-info/RECORD
